{
  "title": "Puppet Skies",
  "subtitle": "How sensing stacks quietly redraw what we see",
  "description": "A book about the invisible sensing infrastructure that filters our horizons—how data, displays, and defaults reshape public imagination and power.",
  "releaseDate": "2026-11-12",
  "status": "coming-soon",
  "formats": [
    { "label": "Amazon", "url": "https://www.amazon.com/dp/B0GKS9WVWL" },
    { "label": "eBook", "url": "https://www.amazon.com/dp/B0GKS9WVWL" }
  ],
  "retailers": [
    { "label": "Amazon", "url": "https://www.amazon.com/dp/B0GKS9WVWL" },
    { "label": "Bookshop", "url": "https://draft2digital.com/book/4109629" }
  ],
  "coverImage": "/images/books/puppet-skies/cover.jpg"
}
